figwizz/__init__.py
figwizz/colors.py
figwizz/convert.py
figwizz/display.py
figwizz/generate.py
figwizz/modify.py
figwizz/process.py
figwizz/scrape.py
figwizz/stitchkit.py
figwizz/webkit.py
figwizz/utils/__init__.py
figwizz/utils/environ.py
figwizz/utils/images.py
figwizz/utils/plugins.py
figwizz/workflows/__init__.py
figwizz/workflows/batch.py
figwizz/workflows/cli_opts.py
figwizz/workflows/genai.py
figwizz/workflows/icons.py
figwizz-0.3.0.dist-info/licenses/LICENSE
figwizz-0.3.0.dist-info/METADATA
figwizz-0.3.0.dist-info/WHEEL
figwizz-0.3.0.dist-info/entry_points.txt
figwizz-0.3.0.dist-info/top_level.txt
figwizz-0.3.0.dist-info/RECORD
