Metadata-Version: 2.4
Name: figwizz
Version: 0.3.0
Summary: Toolkit for programmatic figure design
Author-email: Colin Conwell <colinconwell@gmail.com>
License-Expression: GPL-3.0-only
Classifier: Development Status :: 3 - Alpha
Classifier: Intended Audience :: Developers
Classifier: Operating System :: OS Independent
Classifier: Programming Language :: Python :: 3
Classifier: Programming Language :: Python :: 3.7
Requires-Python: >=3.7
License-File: LICENSE
Requires-Dist: numpy>=1.21.0
Requires-Dist: ipython>=8.0.1
Requires-Dist: pillow>=9.0.0
Requires-Dist: python-pptx>=0.6.21
Requires-Dist: pybtex>=0.24.0
Requires-Dist: matplotlib>=3.7.0
Requires-Dist: tqdm>=4.62.0
Requires-Dist: requests>=2.28.0
Requires-Dist: beautifulsoup4>=4.11.0
Provides-Extra: genai
Requires-Dist: litellm>=1.55.0; extra == "genai"
Provides-Extra: pdf
Requires-Dist: PyMuPDF>=1.22.5; extra == "pdf"
Provides-Extra: svg
Requires-Dist: cairosvg>=2.7.0; extra == "svg"
Provides-Extra: dev
Requires-Dist: pytest>=7.0.0; extra == "dev"
Requires-Dist: pytest-cov>=4.0.0; extra == "dev"
Requires-Dist: isort>=5.0.0; extra == "dev"
Requires-Dist: black>=23.0.0; extra == "dev"
Provides-Extra: docs
Requires-Dist: mkdocs>=1.5.0; extra == "docs"
Requires-Dist: mkdocs-material>=9.0.0; extra == "docs"
Requires-Dist: mkdocstrings[python]>=0.20.0; extra == "docs"
Dynamic: license-file
